[
  {
    "id": 50000,
    "name": "오닉스 스플린터",
    "imageName": "legend/battle_axe/50000.png",
    "rarity": "Rarity.legend",
    "type": "WeaponType.battleAxe",
    "baseLevel": 0,
    "baseDamage": 0,
    "criticalChance": 0.08,
    "criticalDamage": 1.8,
    "defensePenetration": 10.0,
    "doubleAttackChance": 0.0,
    "speed": 0.8,
    "baseSellPrice": 0,
    "stack": {
      "enabled": false,
      "currentStacks": 0,
      "maxStacks": 0,
      "damagePerStack": 0
    },
    "skills": [
      {
        "skill_name": "오닉스 각인",
        "skill_type": "passive",
        "skill_description": "보석의 힘이 사용자와 무기를 각성시킨다.",
        "skill_description_detail": "공격력 +50%, 공격속도 +50%, 치명타 확률 +10%, 치명타 배율 +1배, 적중률 +5%",
        "skill_effect": [
          {
            "effect_name": "applyPassiveStatBoost",
            "params": {
              "stat": "damage",
              "value": 1.5,
              "isMultiplicative": true
            }
          },
          {
            "effect_name": "applyPassiveStatBoost",
            "params": {
              "stat": "speed",
              "value": 1.5,
              "isMultiplicative": true
            }
          },
          {
            "effect_name": "applyPassiveStatBoost",
            "params": {
              "stat": "criticalChance",
              "value": 0.1,
              "isMultiplicative": false
            }
          },
          {
            "effect_name": "applyPassiveStatBoost",
            "params": {
              "stat": "criticalDamage",
              "value": 1.0,
              "isMultiplicative": false
            }
          },
          {
            "effect_name": "applyPassiveStatBoost",
            "params": {
              "stat": "accuracy",
              "value": 0.05,
              "isMultiplicative": false
            }
          }
        ]
      }
    ],
    "accuracy": 0.8,
    "description": "오닉스의 강인한 힘을 담은 전투 도끼. 모든 것을 부술 듯한 기운을 내뿜는다.",
    "enhancement": 0,
    "transcendence": 0,
    "investedGold": 0.0,
    "investedEnhancementStones": 0,
    "investedTranscendenceStones": 0
  },
  {
    "id": 50001,
    "name": "그리즐리",
    "imageName": "legend/battle_axe/50001.png",
    "rarity": "Rarity.legend",
    "type": "WeaponType.battleAxe",
    "baseLevel": 200,
    "baseDamage": 0,
    "criticalChance": 0.08,
    "criticalDamage": 1.8,
    "defensePenetration": 25.0,
    "doubleAttackChance": 0.0,
    "speed": 0.8,
    "baseSellPrice": 0,
    "stack": {
      "enabled": false,
      "currentStacks": 0,
      "maxStacks": 0,
      "damagePerStack": 0
    },
    "skills": [
      {
        "skill_name": "곰발",
        "skill_type": "active",
        "skill_description": "강력한 일격으로 눈앞의 적을 가른다.",
        "skill_description_detail": "공격 시 7.5% 확률로 10배의 피해, 쿨타임 5초",
        "skill_effect": [
          {
            "effect_name": "applyMultiplierDamage",
            "params": {
              "chance": 0.075,
              "trigger": "onHit",
              "multiplier": 10.0,
              "cooldown": 5
            }
          }
        ]
      }
    ],
    "accuracy": 0.8,
    "description": "일격에 모든 것을 찢어버리는 거대한 도끼. 마치 곰의 앞발과도 같다.",
    "enhancement": 0,
    "transcendence": 0,
    "investedGold": 0.0,
    "investedEnhancementStones": 0,
    "investedTranscendenceStones": 0
  },
  {
    "id": 50002,
    "name": "무자비한 집행자",
    "imageName": "legend/battle_axe/50002.png",
    "rarity": "Rarity.legend",
    "type": "WeaponType.battleAxe",
    "baseLevel": 400,
    "baseDamage": 0,
    "criticalChance": 0.08,
    "criticalDamage": 1.8,
    "defensePenetration": 30.0,
    "doubleAttackChance": 0.0,
    "speed": 0.8,
    "baseSellPrice": 0,
    "stack": {
      "enabled": false,
      "currentStacks": 0,
      "maxStacks": 0,
      "damagePerStack": 0
    },
    "skills": [
      {
        "skill_name": "처형",
        "skill_type": "passive",
        "skill_description": "단두대의 칼날과 같은 공격으로 적을 처형한다.",
        "skill_description_detail": "공격시 2.5% 확률로 적 처치, 보스의 경우 160,000 추가 피해, 쿨타임 5초",
        "skill_effect": [
          {
            "effect_name": "applyMonsterKill",
            "params": {
              "fixDmg": 160000,
              "trigger": "onHit",
              "chance": 0.025,
              "cooldown": 5
            }
          }
        ]
      }
    ],
    "accuracy": 0.8,
    "description": "죄인의 목을 치던 망나니의 도끼. 공격 시 낮은 확률로 적을 즉시 처형한다.",
    "enhancement": 0,
    "transcendence": 0,
    "investedGold": 0.0,
    "investedEnhancementStones": 0,
    "investedTranscendenceStones": 0
  },
  {
    "id": 50003,
    "name": "가이안트",
    "imageName": "legend/battle_axe/50003.png",
    "rarity": "Rarity.legend",
    "type": "WeaponType.battleAxe",
    "baseLevel": 600,
    "baseDamage": 0,
    "criticalChance": 0.08,
    "criticalDamage": 1.8,
    "defensePenetration": 35.0,
    "doubleAttackChance": 0.0,
    "speed": 0.8,
    "baseSellPrice": 0,
    "stack": {
      "enabled": false,
      "currentStacks": 0,
      "maxStacks": 0,
      "damagePerStack": 0
    },
    "skills": [
      {
        "skill_name": "가이아의 축복",
        "skill_type": "passive",
        "skill_description": "대지의 신 가이아의 축복으로 사용자의 공격력을 대폭 올려준다.",
        "skill_description_detail": "공격력 +200%",
        "skill_effect": [
          {
            "effect_name": "applyPassiveStatBoost",
            "params": {
              "stat": "damage",
              "value": 3.0,
              "isMultiplicative": true
            }
          }
        ]
      },
      {
        "skill_name": "개연성",
        "skill_type": "passive",
        "skill_description": "신의 온전한 축복을 모두 감당하기에는 무기가 완전하지 못하다.",
        "skill_description_detail": "공격속도 -30%, 적중률 -5%",
        "skill_effect": [
          {
            "effect_name": "applyPassiveStatDebuff",
            "params": {
              "stat": "speed",
              "value": 0.3,
              "isMultiplicative": true
            }
          },
          {
            "effect_name": "applyPassiveStatDebuff",
            "params": {
              "stat": "accuracy",
              "value": 0.05,
              "isMultiplicative": false
            }
          }
        ]
      }
    ],
    "accuracy": 0.8,
    "description": "대지의 신 가이아가 직접 단조했다는 전설의 도끼. 강력한 힘을 지녔으나 그 힘을 감당하기에는 무기가 완전하지 못하다.",
    "enhancement": 0,
    "transcendence": 0,
    "investedGold": 0.0,
    "investedEnhancementStones": 0,
    "investedTranscendenceStones": 0
  },
  {
    "id": 50004,
    "name": "은도끼",
    "imageName": "legend/battle_axe/50004.png",
    "rarity": "Rarity.legend",
    "type": "WeaponType.battleAxe",
    "baseLevel": 800,
    "baseDamage": 0,
    "criticalChance": 0.08,
    "criticalDamage": 1.8,
    "defensePenetration": 45.0,
    "doubleAttackChance": 0.0,
    "speed": 0.8,
    "baseSellPrice": 0,
    "stack": {
      "enabled": false,
      "currentStacks": 0,
      "maxStacks": 0,
      "damagePerStack": 0
    },
    "skills": [
      {
        "skill_name": "신선 세트",
        "skill_type": "passive",
        "skill_description": "금도끼를 획득한 적이 있는 경우, 능력치가 대폭 상승한다.",
        "skill_description_detail": "무기 도감에 금도끼가 활성화 되어있는 경우 공격속도 +200%, 적중률 +20%",
        "skill_effect": [
          {
            "effect_name": "applySynergyBonus",
            "params": {
              "stat": "speed",
              "value": 3.0,
              "isMultiplicative": true,
              "targetId": [50005]
            }
          },
          {
            "effect_name": "applySynergyBonus",
            "params": {
              "stat": "accuracy",
              "value": 0.2,
              "isMultiplicative": false,
              "targetId": [50005]
            }
          }
        ]
      }
    ],
    "accuracy": 0.8,
    "description": "산 속의 패왕 신선이 사용하던 도끼. 겉보기엔 평범한 은도끼이지만 금도끼를 획득한 적이 있는 경우, 능력치가 대폭 상승한다.",
    "enhancement": 0,
    "transcendence": 0,
    "investedGold": 0.0,
    "investedEnhancementStones": 0,
    "investedTranscendenceStones": 0
  },
  {
    "id": 50005,
    "name": "금도끼",
    "imageName": "legend/battle_axe/50005.png",
    "rarity": "Rarity.legend",
    "type": "WeaponType.battleAxe",
    "baseLevel": 800,
    "baseDamage": 0,
    "criticalChance": 0.08,
    "criticalDamage": 1.8,
    "defensePenetration": 45.0,
    "doubleAttackChance": 0.0,
    "speed": 0.8,
    "baseSellPrice": 0,
    "stack": {
      "enabled": false,
      "currentStacks": 0,
      "maxStacks": 0,
      "damagePerStack": 0
    },
    "skills": [
      {
        "skill_name": "신선 세트",
        "skill_type": "passive",
        "skill_description": "은도끼를 획득한 적이 있는 경우, 능력치가 대폭 상승한다.",
        "skill_description_detail": "무기 도감에 금도끼가 활성화 되어있는 경우 공격력 +150%, 적중률 +20%",
        "skill_effect": [
          {
            "effect_name": "applySynergyBonus",
            "params": {
              "stat": "damage",
              "value": 2.5,
              "isMultiplicative": true,
              "targetId": [50005]
            }
          },
          {
            "effect_name": "applySynergyBonus",
            "params": {
              "stat": "accuracy",
              "value": 0.2,
              "isMultiplicative": false,
              "targetId": [50005]
            }
          }
        ]
      }
    ],
    "accuracy": 0.8,
    "description": "산 속의 패왕 신선이 사용하던 도끼. 겉보기엔 평범한 금도끼이지만 은도끼를 획득한 적이 있는 경우, 능력치가 대폭 상승한다.",
    "enhancement": 0,
    "transcendence": 0,
    "investedGold": 0.0,
    "investedEnhancementStones": 0,
    "investedTranscendenceStones": 0
  },
  {
    "id": 50006,
    "name": "신성한 파편 - 척추",
    "imageName": "legend/battle_axe/50006.png",
    "rarity": "Rarity.legend",
    "type": "WeaponType.battleAxe",
    "baseLevel": 1000,
    "baseDamage": 0,
    "criticalChance": 0.08,
    "criticalDamage": 1.8,
    "defensePenetration": 50.0,
    "doubleAttackChance": 0.0,
    "speed": 0.8,
    "baseSellPrice": 0,
    "stack": {
      "enabled": false,
      "currentStacks": 0,
      "maxStacks": 0,
      "damagePerStack": 0
    },
    "skills": [
      {
        "skill_name": "정화",
        "skill_type": "passive",
        "skill_description": "성물이 선과 악을 구분해 전투를 돕는다.",
        "skill_description_detail": "언데드·데몬 종족에게 추가 피해 +100%, 신성·천사 종족에게 추가 피해 -30%",
        "skill_effect": [
          {
            "effect_name": "applyPassiveBonusDamageToRace",
            "params": { "race": "undead", "multiplier": 1 }
          },
          {
            "effect_name": "applyPassiveBonusDamageToRace",
            "params": { "race": "demon", "multiplier": 1 }
          },
          {
            "effect_name": "applyPassivePenaltyDamageToRace",
            "params": { "race": "divine", "multiplier": 0.3 }
          },
          {
            "effect_name": "applyPassivePenaltyDamageToRace",
            "params": { "race": "angel", "multiplier": 0.3 }
          }
        ]
      },
      {
        "skill_name": "심판",
        "skill_type": "active",
        "skill_description": "성물이 찬란한 빛을 발산해 몬스터를 심판한다.",
        "skill_description_detail": "공격 시 7.5% 확률로 1,000,000 추가 피해, 쿨타임 5초",
        "skill_effect": [
          {
            "effect_name": "applyFixedDamage",
            "params": {
              "chance": 0.075,
              "damage": 1000000,
              "cooldown": 5,
              "trigger": "onHit"
            }
          }
        ]
      }
    ],
    "accuracy": 0.8,
    "description": "신성국의 열다섯 성물 중 하나. 신의 척추로 만들어졌다고 전해진다.",
    "enhancement": 0,
    "transcendence": 0,
    "investedGold": 0.0,
    "investedEnhancementStones": 0,
    "investedTranscendenceStones": 0
  }
]
