[
  {
    "id": 50000,
    "name": "가넷 슬래시",
    "imageName": "legend/scimitar/50000.png",
    "rarity": "Rarity.legend",
    "type": "WeaponType.scimitar",
    "baseLevel": 0,
    "baseDamage": 0,
    "criticalChance": 0.1,
    "criticalDamage": 1.5,
    "defensePenetration": 4.0,
    "doubleAttackChance": 0.0,
    "speed": 1.0,
    "baseSellPrice": 0,
    "stack": {
      "enabled": false,
      "currentStacks": 0,
      "maxStacks": 0,
      "damagePerStack": 0
    },
    "skills": [
      {
        "skill_name": "가넷 각인",
        "skill_type": "passive",
        "skill_description": "보석의 힘이 사용자와 무기를 각성시킨다.",
        "skill_description_detail": "공격력 +50%, 공격속도 +50%, 치명타 확률 +10%, 치명타 배율 +1배, 적중률 +5%",
        "skill_effect": [
          {
            "effect_name": "applyPassiveStatBoost",
            "params": {
              "stat": "damage",
              "value": 1.5,
              "isMultiplicative": true
            }
          },
          {
            "effect_name": "applyPassiveStatBoost",
            "params": {
              "stat": "speed",
              "value": 1.5,
              "isMultiplicative": true
            }
          },
          {
            "effect_name": "applyPassiveStatBoost",
            "params": {
              "stat": "criticalChance",
              "value": 0.1,
              "isMultiplicative": false
            }
          },
          {
            "effect_name": "applyPassiveStatBoost",
            "params": {
              "stat": "criticalDamage",
              "value": 1.0,
              "isMultiplicative": false
            }
          },
          {
            "effect_name": "applyPassiveStatBoost",
            "params": {
              "stat": "accuracy",
              "value": 0.05,
              "isMultiplicative": false
            }
          }
        ]
      }
    ],
    "accuracy": 0.823,
    "description": "가넷의 깊고 열정적인 붉은 빛을 담은 검. 전투 능력을 크게 끌어올린다.",
    "enhancement": 0,
    "transcendence": 0,
    "investedGold": 0.0,
    "investedEnhancementStones": 0,
    "investedTranscendenceStones": 0
  },
  {
    "id": 50001,
    "name": "블랙 스콜피온",
    "imageName": "legend/scimitar/50001.png",
    "rarity": "Rarity.legend",
    "type": "WeaponType.scimitar",
    "baseLevel": 200,
    "baseDamage": 0,
    "criticalChance": 0.1,
    "criticalDamage": 1.5,
    "defensePenetration": 20.0,
    "doubleAttackChance": 0.0,
    "speed": 1.0,
    "baseSellPrice": 0,
    "stack": {
      "enabled": false,
      "currentStacks": 0,
      "maxStacks": 0,
      "damagePerStack": 0
    },
    "skills": [
      {
        "skill_name": "맹독 주입",
        "skill_type": "active",
        "skill_description": "치명적인 맹독을 주입한다.",
        "skill_description_detail": "공격 시 7.5% 확률로 5초간 중독, 초당 최대 체력의 8% 피해, 최대 데미지 166,000, 쿨타임 5초",
        "skill_effect": [
          {
            "effect_name": "applyPoison",
            "params": {
              "chance": 0.075,
              "percentPerSecond": 0.08,
              "maxDmg": 166000,
              "duration": 5,
              "trigger": "onHit",
              "stackable": false,
              "cooldown": 5
            }
          }
        ]
      },
      {
        "skill_name": "사막의 매복자",
        "skill_type": "active",
        "skill_description": "상대가 방심한 틈을 타 치명적인 공격을 가한다.",
        "skill_description_detail": "치명타 확률 +30%, 치명타 배율 +2배",
        "skill_effect": [
          {
            "effect_name": "applyPassiveStatBoost",
            "params": {
              "stat": "criticalChance",
              "value": 0.3,
              "isMultiplicative": false
            }
          },
          {
            "effect_name": "applyPassiveStatBoost",
            "params": {
              "stat": "criticalDamage",
              "value": 2.0,
              "isMultiplicative": false
            }
          }
        ]
      }
    ],
    "accuracy": 0.823,
    "description": "사막의 극독을 품은 블랙 스콜피온을 본따 만든 시미터. 중독된 생물은 살아남을 수 없다.",
    "enhancement": 0,
    "transcendence": 0,
    "investedGold": 0.0,
    "investedEnhancementStones": 0,
    "investedTranscendenceStones": 0
  },
  {
    "id": 50002,
    "name": "저주받은 도굴꾼",
    "imageName": "legend/scimitar/50002.png",
    "rarity": "Rarity.legend",
    "type": "WeaponType.scimitar",
    "baseLevel": 400,
    "baseDamage": 0,
    "criticalChance": 0.1,
    "criticalDamage": 1.5,
    "defensePenetration": 24.0,
    "doubleAttackChance": 0.0,
    "speed": 1.0,
    "baseSellPrice": 0,
    "stack": {
      "enabled": false,
      "currentStacks": 0,
      "maxStacks": 0,
      "damagePerStack": 0
    },
    "skills": [
      {
        "skill_name": "파라오의 저주",
        "skill_type": "passive",
        "skill_description": "강력한 저주가 사용자의 이성을 파괴한다.",
        "skill_description_detail": "공격력 +444%",
        "skill_effect": [
          {
            "effect_name": "applyPassiveStatBoost",
            "params": {
              "stat": "damage",
              "value": 5.44,
              "isMultiplicative": true
            }
          }
        ]
      },
      {
        "skill_name": "파라오의 저주 Ⅱ",
        "skill_type": "passive",
        "skill_description": "사용자가 이지를 상실한다.",
        "skill_description_detail": "클릭 공격 비활성화",
        "skill_effect": [{ "effect_name": "disableManualAttack", "params": {} }]
      }
    ],
    "accuracy": 0.823,
    "description": "손에 쥐는 동시에 이성을 잃게 만드는 무기. 수많은 도굴꾼들이 이 무기를 탐내다 저주에 걸려 미쳐버렸다.",
    "enhancement": 0,
    "transcendence": 0,
    "investedGold": 0.0,
    "investedEnhancementStones": 0,
    "investedTranscendenceStones": 0
  },
  {
    "id": 50002,
    "name": "영혼 탐식자",
    "imageName": "legend/scimitar/50002.png",
    "rarity": "Rarity.legend",
    "type": "WeaponType.scimitar",
    "baseLevel": 600,
    "baseDamage": 0,
    "criticalChance": 0.1,
    "criticalDamage": 1.5,
    "defensePenetration": 28.0,
    "doubleAttackChance": 0.0,
    "speed": 1.0,
    "baseSellPrice": 0,
    "stack": {
      "enabled": true,
      "currentStacks": 0,
      "maxStacks": 444,
      "damagePerStack": 90
    },
    "skills": [
      {
        "skill_name": "영혼 탐식",
        "skill_type": "active",
        "skill_description": "처치한 적의 영혼을 삼켜 힘으로 바꾼다.",
        "skill_description_detail": "적 처치 시 무기 공격력 +90, 최대 444중첩",
        "skill_effect": [
          {
            "effect_name": "increaseStat",
            "params": { "stat": "stack.currentStacks", "increment": 1 }
          }
        ]
      }
    ],
    "accuracy": 0.823,
    "description": "죽은 자의 혼을 심판하는 괴물인 아미트의 두개골로 만든 시미터. 처치한 적의 영혼을 수확한다.",
    "enhancement": 0,
    "transcendence": 0,
    "investedGold": 0.0,
    "investedEnhancementStones": 0,
    "investedTranscendenceStones": 0
  },
  {
    "id": 50004,
    "name": "탈라예 쿠비라",
    "imageName": "legend/scimitar/50004.png",
    "rarity": "Rarity.legend",
    "type": "WeaponType.scimitar",
    "baseLevel": 800,
    "baseDamage": 0,
    "criticalChance": 0.1,
    "criticalDamage": 1.5,
    "defensePenetration": 36.0,
    "doubleAttackChance": 0.0,
    "speed": 1.0,
    "baseSellPrice": 0,
    "stack": {
      "enabled": false,
      "currentStacks": 0,
      "maxStacks": 0,
      "damagePerStack": 0
    },
    "skills": [
      {
        "skill_name": "영원한 번영",
        "skill_type": "passive",
        "skill_description": "소지하는 것만으로도 엄청난 부를 불러온다. ",
        "skill_description_detail": "골드 획득량 +200%",
        "skill_effect": [
          {
            "effect_name": "applyGoldGainBoost",
            "params": { "multiplier": 3.0 }
          }
        ]
      },
      {
        "skill_name": "화려한 소비",
        "skill_type": "passive",
        "skill_description": "보유한 골드를 소모해 적에게 추가 피해를 입힌다. ",
        "skill_description_detail": "골드 소모량 500G, 무기 공격력의 100% 추가 피해",
        "skill_effect": [
          {
            "effect_name": "applyGoldConsumePerHitDamage",
            "params": {
              "goldPerHit": 500,
              "percentDamageBonus": 1.0,
              "cooldown": 0
            }
          }
        ]
      }
    ],
    "accuracy": 0.823,
    "description": "부와 행운의 신 쿠베라의 황금을 깎아 만든 시미터. 골드 획득량이 증가하며, 골드를 소모해 추가 데미지를 준다.",
    "enhancement": 0,
    "transcendence": 0,
    "investedGold": 0.0,
    "investedEnhancementStones": 0,
    "investedTranscendenceStones": 0
  },
  {
    "id": 50005,
    "name": "신성한 파편 - 갈비뼈",
    "imageName": "legend/scimitar/50005.png",
    "rarity": "Rarity.legend",
    "type": "WeaponType.scimitar",
    "baseLevel": 1000,
    "baseDamage": 0,
    "criticalChance": 0.1,
    "criticalDamage": 1.5,
    "defensePenetration": 40.0,
    "doubleAttackChance": 0.0,
    "speed": 1.0,
    "baseSellPrice": 0,
    "stack": {
      "enabled": false,
      "currentStacks": 0,
      "maxStacks": 0,
      "damagePerStack": 0
    },
    "skills": [
      {
        "skill_name": "정화",
        "skill_type": "passive",
        "skill_description": "성물이 선과 악을 구분해 전투를 돕는다.",
        "skill_description_detail": "언데드·데몬 종족에게 추가 피해 +100%, 신성·천사 종족에게 추가 피해 -30%",
        "skill_effect": [
          {
            "effect_name": "applyPassiveBonusDamageToRace",
            "params": { "race": "undead", "multiplier": 1 }
          },
          {
            "effect_name": "applyPassiveBonusDamageToRace",
            "params": { "race": "demon", "multiplier": 1 }
          },
          {
            "effect_name": "applyPassivePenaltyDamageToRace",
            "params": { "race": "divine", "multiplier": 0.3 }
          },
          {
            "effect_name": "applyPassivePenaltyDamageToRace",
            "params": { "race": "angel", "multiplier": 0.3 }
          }
        ]
      },
      {
        "skill_name": "심판",
        "skill_type": "active",
        "skill_description": "성물이 찬란한 빛을 발산해 몬스터를 심판한다.",
        "skill_description_detail": "공격 시 7.5% 확률로 1,000,000 추가 피해, 쿨타임 5초",
        "skill_effect": [
          {
            "effect_name": "applyFixedDamage",
            "params": {
              "chance": 0.075,
              "damage": 1000000,
              "cooldown": 5,
              "trigger": "onHit"
            }
          }
        ]
      }
    ],
    "accuracy": 0.823,
    "description": "신성국의 열다섯 성물 중 하나. 신의 갈비뼈로 만들어졌다고 전해진다.",
    "enhancement": 0,
    "transcendence": 0,
    "investedGold": 0.0,
    "investedEnhancementStones": 0,
    "investedTranscendenceStones": 0
  }
]
